DirichletMagmaMix/__init__.py
DirichletMagmaMix-1.0.dist-info/LICENSE
DirichletMagmaMix-1.0.dist-info/METADATA
DirichletMagmaMix-1.0.dist-info/WHEEL
DirichletMagmaMix-1.0.dist-info/top_level.txt
DirichletMagmaMix-1.0.dist-info/RECORD
