Metadata-Version: 2.1
Name: DirichletMagmaMix
Version: 1.0
Summary: A python library for modelling partial melt aggregation
Home-page: https://github.com/simonwmatthews/DirichletMagmaMix
Author: Simon Matthews
Author-email: simonm@hi.is
Classifier: Programming Language :: Python :: 3
Classifier: License :: OSI Approved :: MIT License
Classifier: Operating System :: OS Independent
Requires-Python: >=3.6
License-File: LICENSE
Requires-Dist: pandas (>=1.3.5)
Requires-Dist: numpy (>=1.21.5)
Requires-Dist: pyMelt (>=2.0)
